[
  {
    "commentId": 233234,
    "codingamerId": 3589590,
    "commentableId": 33826373,
    "responseCount": 0,
    "upVotes": 0,
    "downVotes": 0,
    "votableId": 34517612,
    "userVoteValue": 0,
    "nickname": "Edjy",
    "content": "Validator 5 had an extra \\n, causing an undetectable error for some people. Please make sure you check all testcases and validators before submitting a contribution.",
    "codingamerHandle": "674fbda5df945919eb37269de9e598e10959853",
    "avatar": 43965748895173,
    "elapsedTime": 49315837000
  },
  {
    "commentId": 232543,
    "codingamerId": 3837733,
    "commentableId": 33826373,
    "responseCount": 0,
    "upVotes": 0,
    "downVotes": 1,
    "votableId": 34495948,
    "userVoteValue": 0,
    "nickname": "Pacem",
    "content": "✅ Approved the contribution.\nComment: Cette contribition est valable est applicable pour un chash of code golfing / fatest",
    "codingamerHandle": "2ab293f25b6a136ced86673235057c4b3377383",
    "avatar": 45365846682657,
    "elapsedTime": 49520642000
  },
  {
    "commentId": 232476,
    "codingamerId": 6022026,
    "commentableId": 33826373,
    "responseCount": 0,
    "upVotes": 0,
    "downVotes": 1,
    "votableId": 34495426,
    "userVoteValue": 0,
    "nickname": "Oximon",
    "content": "✅ Approved the contribution.\nComment: J'accepte cette contribution car l'idée est bien expliquée et le jeu est très facilement résolvable.",
    "codingamerHandle": "f80612ce7db5237b0b7afc82a041ae476202206",
    "avatar": 122322147415700,
    "elapsedTime": 49525642000
  },
  {
    "commentId": 232211,
    "codingamerId": 3479792,
    "commentableId": 33826373,
    "responseCount": 2,
    "upVotes": 2,
    "downVotes": 0,
    "votableId": 34485987,
    "userVoteValue": 0,
    "nickname": "StepBack13",
    "content": "Gungyphant's point hasn't been addressed:\n\"The hint says that it's not solvable by calculating each factorial individually, however print(int(math.factorial(x)/math.factorial(y))) passes all the testcases\"\n\nIf you just remove the erroneous hint, this is approvable.",
    "codingamerHandle": "da2fe4fbf3c0ab008c6dcf304920ec602979743",
    "avatar": 33990586394707,
    "elapsedTime": 49620558000
  },
  {
    "commentId": 231385,
    "codingamerId": 6160950,
    "commentableId": 33826373,
    "responseCount": 0,
    "upVotes": 0,
    "downVotes": 1,
    "votableId": 34466996,
    "userVoteValue": 0,
    "nickname": "__SAG__",
    "content": "✅ Approved the contribution.\nComment: I didnot find any reason to reject it as per my experience",
    "codingamerHandle": "86908d17ff4fb4378fb7d5e6c4fe2ed60590616",
    "avatar": 127055428973824,
    "elapsedTime": 49845844000
  },
  {
    "commentId": 230401,
    "codingamerId": 1751832,
    "commentableId": 33826373,
    "responseCount": 0,
    "upVotes": 0,
    "downVotes": 0,
    "votableId": 34437578,
    "userVoteValue": 0,
    "nickname": "buikikaesu",
    "content": "in your solution code:\n\n# i.e   (5 * 4 * 3 * 2 * 1) / (3 * 2 * 1) = 2 * 1, because the 5 * 4 * 3 cancles out as it's present in the numerator and the denominator.\n\nshould be:\n\n# i.e   (5 * 4 * 3 * 2 * 1) / (3 * 2 * 1) = 5 * 4, because the 3 * 2 * 1 cancles out as it's present in the numerator and the denominator.",
    "codingamerHandle": "cc050e3d3c20554b74852891a35b21f52381571",
    "avatar": 24659390839366,
    "elapsedTime": 50123884000
  },
  {
    "commentId": 227969,
    "codingamerId": 3820735,
    "commentableId": 33826373,
    "responseCount": 2,
    "upVotes": 3,
    "downVotes": 0,
    "votableId": 34360342,
    "userVoteValue": 0,
    "nickname": "Gungyphant",
    "content": "The hint says that it's not solvable by calculating each factorial individually, however print(int(math.factorial(x)/math.factorial(y))) passes all the testcases",
    "codingamerHandle": "8a63663512ee6aa18e5bdf4ab38ea9b05370283",
    "avatar": 104190587274785,
    "elapsedTime": 50800551000
  },
  {
    "commentId": 220441,
    "codingamerId": 2874091,
    "commentableId": 33826373,
    "responseCount": 4,
    "upVotes": 1,
    "downVotes": 0,
    "votableId": 33976848,
    "userVoteValue": 0,
    "nickname": "5DN1L",
    "content": "Constraints\n* Please state the lower limits of x and y.\n\nCases\n* Each pair of test and validator should be similar. For example, it's better for\n\n  • High Test Case and Random Test Case 4 to be paired up (as both involve large x and large y),\n\n  • Random Test Case 1 to be paired up with a validator where x = y.\n\nThanks.",
    "codingamerHandle": "bbb8f47ea4601179303c20acdbf5fb6c1904782",
    "onlineSince": 1770727666105,
    "avatar": 134264063920528,
    "elapsedTime": 52684830000
  },
  {
    "commentId": 220439,
    "codingamerId": 5748659,
    "commentableId": 33826373,
    "responseCount": 5,
    "upVotes": 0,
    "downVotes": 0,
    "votableId": 33976819,
    "userVoteValue": 0,
    "content": "i think this is too easy for clash. here is my solution in python which is a 1 line solution.\nprint(prod(range(y + 1, x + 1)))",
    "codingamerHandle": "dff504e289720a4e94fe5ee24f86d26b9568475",
    "elapsedTime": 52684994000
  },
  {
    "commentId": 220442,
    "codingamerId": 2874091,
    "commentableId": 33826373,
    "responseCount": 0,
    "upVotes": 2,
    "downVotes": 0,
    "parentCommentId": 220439,
    "votableId": 33976870,
    "userVoteValue": 0,
    "nickname": "5DN1L",
    "content": "You still need to import math.",
    "codingamerHandle": "bbb8f47ea4601179303c20acdbf5fb6c1904782",
    "onlineSince": 1770727666105,
    "avatar": 134264063920528,
    "elapsedTime": 52684744000
  },
  {
    "commentId": 220448,
    "codingamerId": 5714269,
    "commentableId": 33826373,
    "responseCount": 0,
    "upVotes": 1,
    "downVotes": 0,
    "parentCommentId": 220441,
    "votableId": 33977349,
    "userVoteValue": 0,
    "nickname": "joshh0444",
    "content": "Thank you I have now made these additions.",
    "codingamerHandle": "d9e6f58de406a4eff252954bf2987daf9624175",
    "elapsedTime": 52681739000
  },
  {
    "commentId": 228681,
    "codingamerId": 5829515,
    "commentableId": 33826373,
    "responseCount": 0,
    "upVotes": 1,
    "downVotes": 0,
    "parentCommentId": 227969,
    "votableId": 34382865,
    "userVoteValue": 0,
    "nickname": "Stef_3",
    "content": "This could be fixed by removing constraint 0 < x < 1000 and 0 < y < 1000 while keeping the constraint x!/y! < 2,147,483,647.\n\nFor instance with x = 1,000,001 and y = 1,000,000, the output should be 1,000,001, but math.factorial(x)//math.factorial(y) times out.",
    "codingamerHandle": "9f2646b70e1699fc7b6101dd0b5eb88a5159285",
    "avatar": 135978326596201,
    "elapsedTime": 50625465000
  },
  {
    "commentId": 232540,
    "codingamerId": 5829515,
    "commentableId": 33826373,
    "responseCount": 0,
    "upVotes": 0,
    "downVotes": 0,
    "parentCommentId": 232211,
    "votableId": 34495836,
    "userVoteValue": 0,
    "nickname": "Stef_3",
    "content": "Instead of removing the hint, you can make the hint true by adding some testcases where x and y are both large, but x-y is small.\n\nFor instance y = 1000000 and x=y+1\n\nThis requires removing constraint 0 < x < 1000 and 0 < y < 1000 while keeping constraint x!/y! < 2,147,483,647.\n\nI think this is a great Clash, the only reason I haven't voted to approve yet is because this issue hasn't been addressed.",
    "codingamerHandle": "9f2646b70e1699fc7b6101dd0b5eb88a5159285",
    "avatar": 135978326596201,
    "elapsedTime": 49521816000
  },
  {
    "commentId": 232606,
    "codingamerId": 3479792,
    "commentableId": 33826373,
    "responseCount": 0,
    "upVotes": 0,
    "downVotes": 0,
    "parentCommentId": 232211,
    "votableId": 34497731,
    "userVoteValue": 0,
    "nickname": "StepBack13",
    "content": "Since this has been approved now, I just removed the hint for now until the author can address this.\n\nHint text below for easy copying back in later:\n\n\n<<HINT:>> This is not solvable by calculating each factorial individually.",
    "codingamerHandle": "da2fe4fbf3c0ab008c6dcf304920ec602979743",
    "avatar": 33990586394707,
    "elapsedTime": 49506943000
  },
  {
    "commentId": 229970,
    "codingamerId": 3479792,
    "commentableId": 33826373,
    "responseCount": 0,
    "upVotes": 1,
    "downVotes": 0,
    "parentCommentId": 227969,
    "votableId": 34424228,
    "userVoteValue": 0,
    "nickname": "StepBack13",
    "content": "Are you planning to fix this or not? Because for now the statement is untrue.",
    "codingamerHandle": "da2fe4fbf3c0ab008c6dcf304920ec602979743",
    "avatar": 33990586394707,
    "elapsedTime": 50246081000
  },
  {
    "commentId": 220450,
    "codingamerId": 2874091,
    "commentableId": 33826373,
    "responseCount": 0,
    "upVotes": 1,
    "downVotes": 0,
    "parentCommentId": 220441,
    "votableId": 33977378,
    "userVoteValue": 0,
    "nickname": "5DN1L",
    "content": "Thank you.\n\nCould you please add a 5th pair of cases (test + validator) where x = y?",
    "codingamerHandle": "bbb8f47ea4601179303c20acdbf5fb6c1904782",
    "onlineSince": 1770727666105,
    "avatar": 134264063920528,
    "elapsedTime": 52681490000
  },
  {
    "commentId": 220451,
    "codingamerId": 5714269,
    "commentableId": 33826373,
    "responseCount": 0,
    "upVotes": 2,
    "downVotes": 0,
    "parentCommentId": 220441,
    "votableId": 33977410,
    "userVoteValue": 0,
    "nickname": "joshh0444",
    "content": "Done. :) Thank you.",
    "codingamerHandle": "d9e6f58de406a4eff252954bf2987daf9624175",
    "elapsedTime": 52681273000
  },
  {
    "commentId": 220452,
    "codingamerId": 2874091,
    "commentableId": 33826373,
    "responseCount": 0,
    "upVotes": 1,
    "downVotes": 0,
    "parentCommentId": 220441,
    "votableId": 33977823,
    "userVoteValue": 0,
    "nickname": "5DN1L",
    "content": "Looks good. Thank you too. :)",
    "codingamerHandle": "bbb8f47ea4601179303c20acdbf5fb6c1904782",
    "onlineSince": 1770727666105,
    "avatar": 134264063920528,
    "elapsedTime": 52678170000
  },
  {
    "commentId": 220443,
    "codingamerId": 2874091,
    "commentableId": 33826373,
    "responseCount": 0,
    "upVotes": 1,
    "downVotes": 0,
    "parentCommentId": 220439,
    "votableId": 33976913,
    "userVoteValue": 0,
    "nickname": "5DN1L",
    "content": "I think shortest mode can still be challenging. And players of other programming languages will have to find other tricks.",
    "codingamerHandle": "bbb8f47ea4601179303c20acdbf5fb6c1904782",
    "onlineSince": 1770727666105,
    "avatar": 134264063920528,
    "elapsedTime": 52684534000
  },
  {
    "commentId": 220447,
    "codingamerId": 5748659,
    "commentableId": 33826373,
    "responseCount": 0,
    "upVotes": 0,
    "downVotes": 0,
    "parentCommentId": 220439,
    "votableId": 33977297,
    "userVoteValue": 0,
    "content": "true but i was just talking about just typing this in where it says 'print(answer)'",
    "codingamerHandle": "dff504e289720a4e94fe5ee24f86d26b9568475",
    "elapsedTime": 52682073000
  },
  {
    "commentId": 220449,
    "codingamerId": 2874091,
    "commentableId": 33826373,
    "responseCount": 0,
    "upVotes": 1,
    "downVotes": 0,
    "parentCommentId": 220439,
    "votableId": 33977372,
    "userVoteValue": 0,
    "nickname": "5DN1L",
    "content": "All right, understood.",
    "codingamerHandle": "bbb8f47ea4601179303c20acdbf5fb6c1904782",
    "onlineSince": 1770727666105,
    "avatar": 134264063920528,
    "elapsedTime": 52681533000
  },
  {
    "commentId": 231088,
    "codingamerId": 3765537,
    "commentableId": 33826373,
    "responseCount": 0,
    "upVotes": 0,
    "downVotes": 0,
    "parentCommentId": 220439,
    "votableId": 34456387,
    "userVoteValue": 0,
    "nickname": "Sentience",
    "content": "I disagree. Not everyone knows about factorial.\nThey discover the concept recently, maybe during this clash.\nThey read the short explanation, but maybe do not realize how strong the factorial's growth is.\nThen, they need to figure out that dividing two factorials leads to a cancellation of many factors.\n\nMaybe I'm wrong, but for now I still imagine that one can discover/learn math skills through clashes ; not always that easy for people able to provide a one line solution.",
    "codingamerHandle": "7d1ffa66b986cdaedb9d55978eb961597355673",
    "avatar": 141441504003573,
    "elapsedTime": 49953444000
  }
]