{
  "id": 37867,
  "activeVersion": 19,
  "score": 18,
  "votableId": 26086736,
  "codingamerId": 5062387,
  "views": 242,
  "commentableId": 25963316,
  "title": "Space Checking",
  "status": "ACCEPTED",
  "type": "CLASHOFCODE",
  "nickname": "Tenclea",
  "publicHandle": "378675dd9a7d5e8ed8177de8cd197d68afd74",
  "codingamerHandle": "99a4ddbc0558ad0916e22f2ba36d1fbf7832605",
  "lastVersion": {
    "version": 19,
    "autocloseTime": 1669594741190,
    "data": {
      "title": "Space Checking",
      "topics": [],
      "fastest": true,
      "reverse": true,
      "shortest": true,
      "solution": "float convToBytes(float size, char *unit) {\n  char tab[5] = {'B', 'K', 'M', 'G', 'T'};\n  for (int i = 0; i < 5 && tab[i] != unit[0]; i++)\n    size *= 1024;\n  return size;\n}\n\nvoid printSize(float size) {\n  char *tab[5] = {\"B\", \"KiB\", \"MiB\", \"GiB\", \"TiB\"};\n  int i;\n  for (i = 0; size / 1024 > 1; i++)\n    size /= 1024;\n\n  if ((int)size == size)\n    printf(\"%d %s\", (int)size, tab[i]);\n  else\n    printf(\"%.1f %s\", size, tab[i]);\n}\n\nint main() {\n  float disk_size;\n  char disk_unit[3];\n  scanf(\"%f%s\", &disk_size, disk_unit);\n\n  float file_size;\n  char file_unit[3];\n  scanf(\"%f%s\", &file_size, file_unit);\n\n  float dsl = convToBytes(disk_size, disk_unit);\n  float fs = convToBytes(file_size, file_unit);\n  float l = dsl - fs;\n\n  if (l < 0)\n    printf(\"Not enough space\\n\");\n  else\n    printSize(l);\n\n  return 0;\n}",
      "statement": "Alex wants to download a file sent by his friend, Duo, but they do not know whether they have <<enough storage space left>> on their computer. Help them <<find the remaining space>> on their drive after downloading the file !",
      "testCases": [
        {
          "title": "Warming up",
          "isTest": true,
          "testIn": "15 MiB\n2048 KiB",
          "testOut": "13 MiB",
          "isValidator": false,
          "needValidation": true
        },
        {
          "title": "Warming up (Validator)",
          "isTest": false,
          "testIn": "1 KiB\n1024 B",
          "testOut": "0 B",
          "isValidator": true,
          "needValidation": true
        },
        {
          "title": "Decimal values",
          "isTest": true,
          "testIn": "10 MiB\n512 KiB",
          "testOut": "9.5 MiB",
          "isValidator": false,
          "needValidation": true
        },
        {
          "title": "Decimal values (Validator)",
          "isTest": false,
          "testIn": "4 GiB\n1536 MiB",
          "testOut": "2.5 GiB",
          "isValidator": true,
          "needValidation": true
        },
        {
          "title": "Two layers down",
          "isTest": true,
          "testIn": "15 MiB\n15728639 B",
          "testOut": "1 B",
          "isValidator": false,
          "needValidation": true
        },
        {
          "title": "Two layers down (Validator)",
          "isTest": false,
          "testIn": "5 TiB\n1048576 MiB",
          "testOut": "4 TiB",
          "isValidator": true,
          "needValidation": true
        },
        {
          "title": "Decimal input & output",
          "isTest": true,
          "testIn": "2 GiB\n0.5 GiB",
          "testOut": "1.5 GiB",
          "isValidator": false,
          "needValidation": true
        },
        {
          "title": "Decimal input & output (Validator)",
          "isTest": false,
          "testIn": "5.5 KiB\n1024 B",
          "testOut": "4.5 KiB",
          "isValidator": true,
          "needValidation": true
        },
        {
          "title": "Out of space",
          "isTest": true,
          "testIn": "1000 GiB\n1 TiB",
          "testOut": "Not enough space",
          "isValidator": false,
          "needValidation": true
        },
        {
          "title": "Out of space (Validator)",
          "isTest": false,
          "testIn": "1023 B\n1 KiB",
          "testOut": "Not enough space",
          "isValidator": true,
          "needValidation": true
        }
      ],
      "constraints": "0 B < Sizes of the disk and file < 1024 TiB\nUnits can be one of : {{B}}, {{KiB}}, {{MiB}}, {{GiB}} and {{TiB}}.\nIf the result is not an integer, then it should be rounded down to one decimal place.",
      "stubGenerator": "read diskSize:float diskUnit:word(3)\nread fileSize:float fileUnit:word(3)\n\nwrite Space left\n\nINPUT\ndiskSize: The amount of space left on the disk\nfileSize: The size of the downloaded file\n\nOUTPUT\n'Not enough space' or the amount of space left\n\nSTATEMENT\nGood luck ! :)",
      "inputDescription": "<<Line 1 :>> The amount of space left on the drive containing a float and a unit separated by a space\n<<Line 2 :>> The size of the downloaded file containing a float and a unit separated by a space",
      "solutionLanguage": "C",
      "outputDescription": "The <<size left on the hard drive>>, expressed in the <<largest binary prefix based on powers of 2>> (i.e. 1024 B should become 1 KiB, 1024 KiB is 1 MiB, etc...) or {{Not enough space}} if there isn't enough space to download the file."
    },
    "draft": false,
    "readyForModeration": true,
    "statementHTML": "<div class=\"statement-body\">\n<div class=\"statement-section statement-goal\">\n   <h2><span class=\"icon icon-goal\">&nbsp;</span><span>Goal </span></h2>\n   <span class=\"question-statement\">Alex wants to download a file sent by his friend, Duo, but they do not know whether they have <strong>enough storage space left</strong> on their computer. Help them <strong>find the remaining space</strong> on their drive after downloading the file !</span>\n</div>\n<div class=\"statement-section statement-protocol\">\n   <div class=\"blk\">\n      <div class=\"title\">Input</div>\n      <div class=\"question-statement-input\"><strong>Line 1 :</strong> The amount of space left on the drive containing a float and a unit separated by a space<br><strong>Line 2 :</strong> The size of the downloaded file containing a float and a unit separated by a space</div>\n   </div>\n   <div class=\"blk\">\n      <div class=\"title\">Output</div>\n      <div class=\"question-statement-output\">The <strong>size left on the hard drive</strong>, expressed in the <strong>largest binary prefix based on powers of 2</strong> (i.e. 1024 B should become 1 KiB, 1024 KiB is 1 MiB, etc...) or <const>Not enough space</const> if there isn't enough space to download the file.</div>\n   </div>\n   <div class=\"blk\">\n      <div class=\"title\">Constraints</div>\n      <div class=\"question-statement-constraints\">0 B &lt; Sizes of the disk and file &lt; 1024 TiB<br>Units can be one of : <const>B</const>, <const>KiB</const>, <const>MiB</const>, <const>GiB</const> and <const>TiB</const>.<br>If the result is not an integer, then it should be rounded down to one decimal place.</div>\n   </div>\n   <div class=\"blk\">\n      <div class=\"title\">Example</div>\n      <div class=\"statement-inout\">\n         <div class=\"statement-inout-in\">\n            <div class=\"title\">Input</div>\n            <pre class=\"question-statement-example-in\">15 MiB\n2048 KiB</pre>\n         </div>\n         <div class=\"statement-inout-out\">\n            <div class=\"title\">Output</div>\n            <pre class=\"question-statement-example-out\">13 MiB</pre>\n         </div>\n      </div>\n   </div>\n</div>"
  },
  "validatedFor": 101243396629,
  "avatar": 106873645042836,
  "commentCount": 17,
  "upVotes": 18,
  "downVotes": 0,
  "validateAction": {
    "actionId": 730850,
    "progress": 1,
    "alreadyDone": false
  },
  "statusHistory": [
    {
      "status": "ACCEPTED",
      "date": 1669486203508,
      "data": {
        "author": "ACTION"
      }
    }
  ],
  "editable": true,
  "draft": false,
  "readyForModeration": true
}