[
  {
    "commentId": 25054,
    "codingamerId": 3416055,
    "commentableId": 12374770,
    "responseCount": 0,
    "upVotes": 1,
    "downVotes": 0,
    "votableId": 12724327,
    "userVoteValue": 0,
    "nickname": "ItsAFeature",
    "content": "✅ Approved the contribution.\nComment: I like the contribution because it's fun and there are no issues any more",
    "codingamerHandle": "ef0672131766e7a47d95bf15379a2d845506143",
    "avatar": 102091024235650,
    "elapsedTime": 188166112000
  },
  {
    "commentId": 25001,
    "codingamerId": 1271129,
    "commentableId": 12374770,
    "responseCount": 0,
    "upVotes": 2,
    "downVotes": 0,
    "votableId": 12682760,
    "userVoteValue": 0,
    "nickname": "Nantoine",
    "content": "I had to read several times the challenge goal to understand what it is about but the challenge is fun and requires interesting skills.\n\nIt does not make sense why the unlabeled animals are decided by majority vote. I think some other story would make more sense but I guess it is more a question of taste.",
    "codingamerHandle": "d87b3bb6ea1dbb6f9a1fea933d7da1de9211721",
    "elapsedTime": 188663983000
  },
  {
    "commentId": 25000,
    "codingamerId": 3382273,
    "commentableId": 12374770,
    "responseCount": 0,
    "upVotes": 1,
    "downVotes": 0,
    "votableId": 12682592,
    "userVoteValue": 0,
    "nickname": "hasleron",
    "content": "✅ Approved the contribution.\nComment: all issues seem to be fixed",
    "codingamerHandle": "474f6e011615f08c477a64bb62e91c2d3722833",
    "avatar": 39607083737997,
    "elapsedTime": 188666290000
  },
  {
    "commentId": 24961,
    "codingamerId": 1817487,
    "commentableId": 12374770,
    "responseCount": 0,
    "upVotes": 1,
    "downVotes": 1,
    "votableId": 12653170,
    "userVoteValue": 0,
    "nickname": "DaanvanderSpek",
    "content": "✅ Approved the contribution.\nComment: Fun challenge, love the animaux",
    "codingamerHandle": "57d4e2d648f302eaffd75371c8199a977847181",
    "avatar": 35400507541472,
    "elapsedTime": 189045083000
  },
  {
    "commentId": 24708,
    "codingamerId": 1569823,
    "commentableId": 12374770,
    "responseCount": 10,
    "upVotes": 3,
    "downVotes": 0,
    "votableId": 12478750,
    "userVoteValue": 0,
    "nickname": "Niako",
    "content": "The statement should explicitly mention the distance used.\n\nThere are sometimes more than \"3 closest neighbors\" in your testcases. For instance, in validator 4, for the 4th input the closest distances^2 are [20, 25, 49, 49, 50, ...] (the \"3 closest\" are actually 4) and for the 5th input they are [1, 2, 10, 10, 10, 17, ...] (the \"3 closest\" are 5). Said otherwise, in your solution code, the line \"nn[distance(animal, (x,y))] = d[animal]\" sometimes overwrites a previous value.\n\nAlso edited to fix the stub.",
    "codingamerHandle": "eb89cbdf69d07106c84edf1d191caaf33289651",
    "avatar": 11911528647474,
    "elapsedTime": 190427123000
  },
  {
    "commentId": 24666,
    "codingamerId": 3623576,
    "commentableId": 12374770,
    "responseCount": 1,
    "upVotes": 2,
    "downVotes": 0,
    "votableId": 12465109,
    "userVoteValue": 0,
    "nickname": "InJustice",
    "content": "I think the statement could be a little bit clearer. How do I use the three nearest neighbors? Do I simply return the majority type of the three neighbors? I like the idea and the skillset needed, but the statement could be more clear about how you develop the output from the inputs. I also thought it took a few reads to understand what the inputs were, and they did not mirror the names found in the generator input.  You can read integers x, y, a instead of string row to make it more clear.",
    "codingamerHandle": "c5acb25c9ddc191621dad72ed4227fb66753263",
    "avatar": 38901884417533,
    "elapsedTime": 190587612000
  },
  {
    "commentId": 24667,
    "codingamerId": 1816832,
    "commentableId": 12374770,
    "responseCount": 0,
    "upVotes": 0,
    "downVotes": 0,
    "parentCommentId": 24666,
    "votableId": 12465328,
    "userVoteValue": 0,
    "nickname": "micheldore",
    "content": "Thanks for your input! I will try and improve the statement. And indeed the generator input could be more specific.",
    "codingamerHandle": "8f95a756c40185694f0b11e47ca6c7df2386181",
    "avatar": 35260901975394,
    "elapsedTime": 190585640000
  },
  {
    "commentId": 24804,
    "codingamerId": 3382273,
    "commentableId": 12374770,
    "responseCount": 0,
    "upVotes": 0,
    "downVotes": 0,
    "parentCommentId": 24708,
    "votableId": 12592780,
    "userVoteValue": 0,
    "nickname": "hasleron",
    "content": "Agreed, validator 4 has no correct outcome since the 3rd neighbour for 4th input can either be a cat or a dog. If both are considered the vote is equal.",
    "codingamerHandle": "474f6e011615f08c477a64bb62e91c2d3722833",
    "avatar": 39607083737997,
    "elapsedTime": 189742450000
  },
  {
    "commentId": 24874,
    "codingamerId": 1816832,
    "commentableId": 12374770,
    "responseCount": 0,
    "upVotes": 0,
    "downVotes": 0,
    "parentCommentId": 24708,
    "votableId": 12620724,
    "userVoteValue": 0,
    "nickname": "micheldore",
    "content": "Thanks for the feedback. I've adjusted the statement and solution code so that whenever there are more than 3  nearest neighbors you should pick whichever one is given first in the input.",
    "codingamerHandle": "8f95a756c40185694f0b11e47ca6c7df2386181",
    "avatar": 35260901975394,
    "elapsedTime": 189390114000
  },
  {
    "commentId": 24877,
    "codingamerId": 1569823,
    "commentableId": 12374770,
    "responseCount": 0,
    "upVotes": 0,
    "downVotes": 0,
    "parentCommentId": 24708,
    "votableId": 12621261,
    "userVoteValue": 0,
    "nickname": "Niako",
    "content": "Nope, what you did is keeping only the *first point* for the three smallest *distinct distances*, but this unfortunately doesn't make much sense...\nFor instance, in the 9th case of validator 2, the sorted distances^2 are [401, 401, 466, 820, 2041] and you choose to throw away the second 401 to compute the majority on the 3 points at distances [401 (first one), 466, 820], so clearly not the 3 nearest neighbors anymore!..",
    "codingamerHandle": "eb89cbdf69d07106c84edf1d191caaf33289651",
    "avatar": 11911528647474,
    "elapsedTime": 189385822000
  },
  {
    "commentId": 24878,
    "codingamerId": 1816832,
    "commentableId": 12374770,
    "responseCount": 0,
    "upVotes": 0,
    "downVotes": 0,
    "parentCommentId": 24708,
    "votableId": 12621280,
    "userVoteValue": 0,
    "nickname": "micheldore",
    "content": "Ahh, I get it now. I'm gonna take a look at my code",
    "codingamerHandle": "8f95a756c40185694f0b11e47ca6c7df2386181",
    "avatar": 35260901975394,
    "elapsedTime": 189385592000
  },
  {
    "commentId": 24879,
    "codingamerId": 1816832,
    "commentableId": 12374770,
    "responseCount": 0,
    "upVotes": 0,
    "downVotes": 0,
    "parentCommentId": 24708,
    "votableId": 12621345,
    "userVoteValue": 0,
    "nickname": "micheldore",
    "content": "Like this?",
    "codingamerHandle": "8f95a756c40185694f0b11e47ca6c7df2386181",
    "avatar": 35260901975394,
    "elapsedTime": 189385119000
  },
  {
    "commentId": 24881,
    "codingamerId": 1569823,
    "commentableId": 12374770,
    "responseCount": 0,
    "upVotes": 0,
    "downVotes": 0,
    "parentCommentId": 24708,
    "votableId": 12622115,
    "userVoteValue": 0,
    "nickname": "Niako",
    "content": "No, still EXACTLY the same problems as those mentioned in my first message...\nx_x",
    "codingamerHandle": "eb89cbdf69d07106c84edf1d191caaf33289651",
    "avatar": 11911528647474,
    "elapsedTime": 189379339000
  },
  {
    "commentId": 24882,
    "codingamerId": 3382273,
    "commentableId": 12374770,
    "responseCount": 0,
    "upVotes": 0,
    "downVotes": 0,
    "parentCommentId": 24708,
    "votableId": 12622299,
    "userVoteValue": 0,
    "nickname": "hasleron",
    "content": "hey micheldore, what about you make it easy for the coders and yourself and just make sure there are only unique distance values in one set of inputs (also explicitly state this in the description).\n\nOr you could state that if there are more than three neighbours because there are more than one 3rd neighbour, more than two 2nd neighbours, or more than three 1st neighbours, all of them count, in which case there has to be an unambiguous outcome (currently not the case).",
    "codingamerHandle": "474f6e011615f08c477a64bb62e91c2d3722833",
    "avatar": 39607083737997,
    "elapsedTime": 189377450000
  },
  {
    "commentId": 24892,
    "codingamerId": 1816832,
    "commentableId": 12374770,
    "responseCount": 0,
    "upVotes": 0,
    "downVotes": 0,
    "parentCommentId": 24708,
    "votableId": 12627214,
    "userVoteValue": 0,
    "nickname": "micheldore",
    "content": "Ok, conflicting inputs have been removed.",
    "codingamerHandle": "8f95a756c40185694f0b11e47ca6c7df2386181",
    "avatar": 35260901975394,
    "elapsedTime": 189312104000
  },
  {
    "commentId": 24899,
    "codingamerId": 1569823,
    "commentableId": 12374770,
    "responseCount": 0,
    "upVotes": 0,
    "downVotes": 0,
    "parentCommentId": 24708,
    "votableId": 12628899,
    "userVoteValue": 0,
    "nickname": "Niako",
    "content": "No, still the same (val. 4)...",
    "codingamerHandle": "eb89cbdf69d07106c84edf1d191caaf33289651",
    "avatar": 11911528647474,
    "elapsedTime": 189299372000
  },
  {
    "commentId": 24910,
    "codingamerId": 1816832,
    "commentableId": 12374770,
    "responseCount": 0,
    "upVotes": 0,
    "downVotes": 0,
    "parentCommentId": 24708,
    "votableId": 12635112,
    "userVoteValue": 0,
    "nickname": "micheldore",
    "content": "Ok true, missed one. Fixed it now",
    "codingamerHandle": "8f95a756c40185694f0b11e47ca6c7df2386181",
    "avatar": 35260901975394,
    "elapsedTime": 189231224000
  }
]