{
  "id": 5348,
  "activeVersion": 20,
  "score": 7,
  "votableId": 14746839,
  "codingamerId": 1527403,
  "views": 196,
  "commentableId": 14666061,
  "title": "SnooZzZzZz...",
  "status": "ACCEPTED",
  "type": "CLASHOFCODE",
  "nickname": "Di_Masta",
  "publicHandle": "53480da8a2a5b8266155535a2ce00d1f8095",
  "codingamerHandle": "9c85c6ec7a1c680811128c2ac32a30623047251",
  "lastVersion": {
    "version": 20,
    "autocloseTime": 1600609406832,
    "data": {
      "title": "SnooZzZzZz...",
      "topics": [],
      "fastest": true,
      "reverse": false,
      "shortest": true,
      "solution": "def v(s):\n    return sum([int(i) * pow(60, 2 - idx) for idx,i in enumerate(s.split(':'))])\n\nt = v(input())\np = v(input())\na = v(input())\ns = int(input())\nm = int(input())\n\nr = a + p + (s * m * 60)\n\nprint(\"No\" if r >= t else [\"No\", \"Yes\"][t - r >= 15 * 60])",
      "statement": "You have to be at the railway station at least {{15}} minutes before the train leaves, you also really enjoy sleeping. Given the time the train leaves [[T]], the time you need to get to the station [[P]], after you leave the bed, the time of  your alarm clock [[A]], the count of times you hit snooze on the alarm [[S]] and the snooze interval [[M]], output {{Yes}} if you'll catch the train, {{No}} otherwise.",
      "testCases": [
        {
          "title": "Example",
          "isTest": true,
          "testIn": "10:00:00\n01:00:00\n08:50:00\n2\n10",
          "testOut": "No",
          "isValidator": false,
          "needValidation": false
        },
        {
          "title": "Example",
          "isTest": false,
          "testIn": "10:00:00\n01:00:00\n08:50:00\n3\n10",
          "testOut": "No",
          "isValidator": true,
          "needValidation": false
        },
        {
          "title": "On time",
          "isTest": true,
          "testIn": "09:35:00\n00:45:00\n08:30:00\n0\n10",
          "testOut": "Yes",
          "isValidator": false,
          "needValidation": false
        },
        {
          "title": "On time",
          "isTest": false,
          "testIn": "09:45:00\n00:35:00\n08:30:00\n0\n20",
          "testOut": "Yes",
          "isValidator": true,
          "needValidation": false
        },
        {
          "title": "Late",
          "isTest": true,
          "testIn": "07:10:00\n01:15:00\n05:30:00\n5\n10",
          "testOut": "No",
          "isValidator": false,
          "needValidation": true
        },
        {
          "title": "Late",
          "isTest": false,
          "testIn": "07:10:00\n01:15:00\n05:30:00\n5\n10",
          "testOut": "No",
          "isValidator": true,
          "needValidation": false
        },
        {
          "title": "After party",
          "isTest": true,
          "testIn": "08:35:44\n01:35:50\n06:00:00\n12\n5",
          "testOut": "No",
          "isValidator": false,
          "needValidation": true
        },
        {
          "title": "After party",
          "isTest": false,
          "testIn": "08:35:50\n00:35:44\n06:00:00\n12\n5",
          "testOut": "Yes",
          "isValidator": true,
          "needValidation": true
        },
        {
          "title": "The Flash",
          "isTest": true,
          "testIn": "05:00:00\n00:00:01\n04:45:00\n0\n1",
          "testOut": "No",
          "isValidator": false,
          "needValidation": false
        },
        {
          "title": "The Flash",
          "isTest": false,
          "testIn": "05:00:00\n00:00:01\n04:44:59\n0\n1",
          "testOut": "Yes",
          "isValidator": true,
          "needValidation": false
        },
        {
          "title": "Far away from town",
          "isTest": true,
          "testIn": "03:33:33\n04:42:15\n22:23:18\n8\n9",
          "testOut": "No",
          "isValidator": false,
          "needValidation": false
        },
        {
          "title": "Far away from town",
          "isTest": false,
          "testIn": "03:33:33\n04:42:15\n22:23:18\n4\n7",
          "testOut": "No",
          "isValidator": true,
          "needValidation": false
        }
      ],
      "constraints": "If you're at the station {{14}} minutes and {{59}} seconds before the train leaves, you're late.\n{{00}} ≤  [[HH]] < {{24}}\n{{00}} ≤  [[MM]],[[SS]] < {{60}}\n{{0}} ≤  [[S]] < {{20}}\n{{0}} ≤  [[M]] < {{60}}",
      "stubGenerator": "read t:string(128)\nread p:string(128)\nread a:string(128)\nread s:int\nread m:int\nwrite Yes/No",
      "inputDescription": "<<Line 1:>> [[T]] string, the time [[HH]]{{:}}[[MM]]{{:}}[[SS]] the train leaves.\n<<Line 2:>> [[P]] string, the time [[HH]]{{:}}[[MM]]{{:}}[[SS]] period you need to get to the station.\n<<Line 3:>> [[A]] string, the time [[HH]]{{:}}[[MM]]{{:}}[[SS]] to which your alarm clock is set.\n<<Line 4:>> [[S]] integer, the count of snoozes you've performed.\n<<Line 5:>> [[M]] integer, the snooze minutes of your alarm clock.",
      "solutionLanguage": "Python3",
      "outputDescription": "{{Yes}} if you'll catch the train, {{No}} otherwise"
    },
    "draft": false,
    "readyForModeration": true,
    "statementHTML": "<div class=\"statement-body\">\n<div class=\"statement-section statement-goal\">\n   <h2><span class=\"icon icon-goal\">&nbsp;</span><span>Goal </span></h2>\n   <span class=\"question-statement\">You have to be at the railway station at least <const>15</const> minutes before the train leaves, you also really enjoy sleeping. Given the time the train leaves <var>T</var>, the time you need to get to the station <var>P</var>, after you leave the bed, the time of  your alarm clock <var>A</var>, the count of times you hit snooze on the alarm <var>S</var> and the snooze interval <var>M</var>, output <const>Yes</const> if you'll catch the train, <const>No</const> otherwise.</span>\n</div>\n<div class=\"statement-section statement-protocol\">\n   <div class=\"blk\">\n      <div class=\"title\">Input</div>\n      <div class=\"question-statement-input\"><strong>Line 1:</strong> <var>T</var> string, the time <var>HH</var><const>:</const><var>MM</var><const>:</const><var>SS</var> the train leaves.<br><strong>Line 2:</strong> <var>P</var> string, the time <var>HH</var><const>:</const><var>MM</var><const>:</const><var>SS</var> period you need to get to the station.<br><strong>Line 3:</strong> <var>A</var> string, the time <var>HH</var><const>:</const><var>MM</var><const>:</const><var>SS</var> to which your alarm clock is set.<br><strong>Line 4:</strong> <var>S</var> integer, the count of snoozes you've performed.<br><strong>Line 5:</strong> <var>M</var> integer, the snooze minutes of your alarm clock.</div>\n   </div>\n   <div class=\"blk\">\n      <div class=\"title\">Output</div>\n      <div class=\"question-statement-output\"><const>Yes</const> if you'll catch the train, <const>No</const> otherwise</div>\n   </div>\n   <div class=\"blk\">\n      <div class=\"title\">Constraints</div>\n      <div class=\"question-statement-constraints\">If you're at the station <const>14</const> minutes and <const>59</const> seconds before the train leaves, you're late.<br><const>00</const> &le;  <var>HH</var> &lt; <const>24</const><br><const>00</const> &le;  <var>MM</var>,<var>SS</var> &lt; <const>60</const><br><const>0</const> &le;  <var>S</var> &lt; <const>20</const><br><const>0</const> &le;  <var>M</var> &lt; <const>60</const></div>\n   </div>\n   <div class=\"blk\">\n      <div class=\"title\">Example</div>\n      <div class=\"statement-inout\">\n         <div class=\"statement-inout-in\">\n            <div class=\"title\">Input</div>\n            <pre class=\"question-statement-example-in\">10:00:00\n01:00:00\n08:50:00\n2\n10</pre>\n         </div>\n         <div class=\"statement-inout-out\">\n            <div class=\"title\">Output</div>\n            <pre class=\"question-statement-example-out\">No</pre>\n         </div>\n      </div>\n   </div>\n</div>"
  },
  "validatedFor": 172394061712,
  "avatar": 5689020242575,
  "commentCount": 15,
  "upVotes": 7,
  "downVotes": 0,
  "validateAction": {
    "actionId": 487295,
    "progress": 1,
    "alreadyDone": false
  },
  "statusHistory": [
    {
      "status": "ACCEPTED",
      "date": 1598336906230,
      "data": {
        "author": "ACTION"
      }
    }
  ],
  "editable": true,
  "draft": false,
  "readyForModeration": true
}