{
  "id": 9753,
  "activeVersion": 12,
  "score": 0,
  "votableId": 22303659,
  "codingamerId": 4718620,
  "views": 395,
  "commentableId": 22192500,
  "title": "Who Let The Dogs Out",
  "status": "ACCEPTED",
  "type": "CLASHOFCODE",
  "nickname": "Hieronymus",
  "publicHandle": "975324b3f2e8982dceac04ee2e4f058be6f8",
  "codingamerHandle": "ccfe87514581d3cc948b573cbeff39b60268174",
  "lastVersion": {
    "version": 12,
    "autocloseTime": 1649409899894,
    "data": {
      "title": "Who Let The Dogs Out",
      "topics": [],
      "fastest": true,
      "reverse": false,
      "shortest": true,
      "solution": "program Answer;\n{$H+}\n{$mode Delphi}\n\nuses\n  sysutils, classes, math, types;\n\nprocedure ParseIn(Inputs: TStrings) ;\nvar Line : string;\nbegin\n  readln(Line);\n  Inputs.Clear;\n  Inputs.Delimiter := ' ';\n  Inputs.DelimitedText := Line;\nend;\n\nvar\n  i, dogMeetCount, diameter, windingcount, distance : Int32;\n  Inputs : TStringList;\nbegin\n  Inputs := TStringList.Create;\n  dogMeetCount:=0;\n  for i := 0 to 2 do\n  begin\n    ParseIn(Inputs);\n    diameter := StrToInt(Inputs[0]);\n    windingcount := StrToInt(Inputs[1]);\n    distance := StrToInt(Inputs[2]);\n    if diameter*Pi*windingcount >= distance*100 then\n      inc(dogMeetCount);\n  end;\n\n  case dogMeetCount of\n    0,1 : WriteLn('Frustration');\n    2   : WriteLn('Little game');\n    3   : WriteLn('Big game');\n  end;\n\n  flush(StdErr); flush(output); // DO NOT REMOVE\nend.\n",
      "statement": "Peter, Paul, and Mary each walk with their dogs in the forest. They come from three separate directions, and are heading to the same play pen (the target). Each person has a retractable dog leash which curls the full length of the leash inside a box (similar to retractable measuring tape).\n\nThe leashes have their own size and parameters. Each leash has a diameter [[d]] and a number [[n]] representing the number of times it wraps around in the box. Distance of the target (the play pen) from the dog is [[t]].\n\nPeter, Paul, and Mary don't move from their original position, and the dogs can only reach areas where the distance to their owner is not more than the full length of the leash. \n\nWould it end in a opportunity to play together in the play pen, or are the dog leash too short?",
      "testCases": [
        {
          "title": "Test 1",
          "isTest": true,
          "testIn": "5 15 19\n8 22 16\n6 26 9",
          "testOut": "Frustration",
          "isValidator": false,
          "needValidation": true
        },
        {
          "title": "Validator 1",
          "isTest": false,
          "testIn": "7 21 21\n8 17 10\n5 39 11",
          "testOut": "Frustration",
          "isValidator": true,
          "needValidation": true
        },
        {
          "title": "Test 2",
          "isTest": true,
          "testIn": "6 49 9\n8 44 11\n10 35 10",
          "testOut": "Big game",
          "isValidator": false,
          "needValidation": true
        },
        {
          "title": "Validator 2",
          "isTest": false,
          "testIn": "8 40 10\n7 37 8\n9 41 11",
          "testOut": "Big game",
          "isValidator": true,
          "needValidation": true
        },
        {
          "title": "Test 3",
          "isTest": true,
          "testIn": "7 50 11\n7 31 6\n8 22 5",
          "testOut": "Little game",
          "isValidator": false,
          "needValidation": true
        },
        {
          "title": "Validator 3",
          "isTest": false,
          "testIn": "6 29 5\n6 42 8\n8 26 6",
          "testOut": "Little game",
          "isValidator": true,
          "needValidation": true
        },
        {
          "title": "Test 4",
          "isTest": true,
          "testIn": "8 29 7\n6 42 10\n8 35 11",
          "testOut": "Frustration",
          "isValidator": false,
          "needValidation": true
        },
        {
          "title": "Validator 4",
          "isTest": false,
          "testIn": "8 14 3\n10 10 4\n7 21 5",
          "testOut": "Frustration",
          "isValidator": true,
          "needValidation": true
        }
      ],
      "constraints": "5 <= [[d]] [cm] <= 10\n10 <= [[n]] <= 50\n2 <= [[t]] [m] <= 30",
      "stubGenerator": "loop 3 read d:int n:int t:int\nwrite answer",
      "inputDescription": "<<{{3}} Lines:>> Each with space separated Values [[d]] (in cm), [[n]] and [[t]] (in m)",
      "solutionLanguage": "Pascal",
      "outputDescription": "The string {{Big game}} if all three dogs can reach the play pen, {{Little game}} when only two dogs can reach the play pen, and {{Frustration}} otherwise."
    },
    "draft": false,
    "readyForModeration": true,
    "statementHTML": "<div class=\"statement-body\">\n<div class=\"statement-section statement-goal\">\n   <h2><span class=\"icon icon-goal\">&nbsp;</span><span>Goal </span></h2>\n   <span class=\"question-statement\">Peter, Paul, and Mary each walk with their dogs in the forest. They come from three separate directions, and are heading to the same play pen (the target). Each person has a retractable dog leash which curls the full length of the leash inside a box (similar to retractable measuring tape).<br><br>The leashes have their own size and parameters. Each leash has a diameter <var>d</var> and a number <var>n</var> representing the number of times it wraps around in the box. Distance of the target (the play pen) from the dog is <var>t</var>.<br><br>Peter, Paul, and Mary don't move from their original position, and the dogs can only reach areas where the distance to their owner is not more than the full length of the leash. <br><br>Would it end in a opportunity to play together in the play pen, or are the dog leash too short?</span>\n</div>\n<div class=\"statement-section statement-protocol\">\n   <div class=\"blk\">\n      <div class=\"title\">Input</div>\n      <div class=\"question-statement-input\"><strong><const>3</const> Lines:</strong> Each with space separated Values <var>d</var> (in cm), <var>n</var> and <var>t</var> (in m)</div>\n   </div>\n   <div class=\"blk\">\n      <div class=\"title\">Output</div>\n      <div class=\"question-statement-output\">The string <const>Big game</const> if all three dogs can reach the play pen, <const>Little game</const> when only two dogs can reach the play pen, and <const>Frustration</const> otherwise.</div>\n   </div>\n   <div class=\"blk\">\n      <div class=\"title\">Constraints</div>\n      <div class=\"question-statement-constraints\">5 &lt;= <var>d</var> [cm] &lt;= 10<br>10 &lt;= <var>n</var> &lt;= 50<br>2 &lt;= <var>t</var> [m] &lt;= 30</div>\n   </div>\n   <div class=\"blk\">\n      <div class=\"title\">Example</div>\n      <div class=\"statement-inout\">\n         <div class=\"statement-inout-in\">\n            <div class=\"title\">Input</div>\n            <pre class=\"question-statement-example-in\">5 15 19\n8 22 16\n6 26 9</pre>\n         </div>\n         <div class=\"statement-inout-out\">\n            <div class=\"title\">Output</div>\n            <pre class=\"question-statement-example-out\">Frustration</pre>\n         </div>\n      </div>\n   </div>\n</div>"
  },
  "validatedFor": 121391392951,
  "avatar": 77855568768142,
  "commentCount": 33,
  "upVotes": 6,
  "downVotes": 6,
  "validateAction": {
    "actionId": 648348,
    "progress": 1,
    "alreadyDone": false
  },
  "denyAction": {
    "actionId": 646414,
    "progress": 0.3333333333333333,
    "alreadyDone": false
  },
  "statusHistory": [
    {
      "status": "ACCEPTED",
      "date": 1649338632711,
      "data": {
        "author": "ACTION"
      }
    }
  ],
  "editable": true,
  "draft": false,
  "readyForModeration": true
}