[
  {
    "commentId": 218285,
    "codingamerId": 3893564,
    "commentableId": 30825495,
    "responseCount": 3,
    "upVotes": 1,
    "downVotes": 0,
    "votableId": 33893897,
    "userVoteValue": 0,
    "nickname": "Andriamanitra",
    "content": "The statement is not clear enough. \"last 5 seconds\"? How am I supposed to know how much time has passed since the last tic? How can the speed be 0 in the last test case even though the wheel must have turned to generate a tic?? Solving a clash shouldn't require players to guess what the author actually meant.\n\nThe proposed solution is NOT calculating the average speed for the last 5 seconds since it's looking at the first and last tic. They are not 5 seconds apart in the test cases!",
    "codingamerHandle": "8931375f2caabaa3c46fc9401a856edf4653983",
    "avatar": 46641547586781,
    "elapsedTime": 53323954000
  },
  {
    "commentId": 157976,
    "codingamerId": 5398208,
    "commentableId": 30825495,
    "responseCount": 0,
    "upVotes": 0,
    "downVotes": 0,
    "votableId": 31389908,
    "userVoteValue": 0,
    "nickname": "Gaby92",
    "content": "Very complicated one for a clash :D",
    "codingamerHandle": "b03ef82780a10488bb13a9016c28d99b8028935",
    "elapsedTime": 72313377000
  },
  {
    "commentId": 153671,
    "codingamerId": 5636162,
    "commentableId": 30825495,
    "responseCount": 1,
    "upVotes": 0,
    "downVotes": 0,
    "votableId": 31232956,
    "userVoteValue": 0,
    "nickname": "MartinienGABA",
    "content": "There is a probleme when len(buffer)=2. In this case buffer[-1]-buffer[1] = 0.",
    "codingamerHandle": "10df5c108ed9c02fd608dac606cba8c22616365",
    "avatar": 109418224116427,
    "elapsedTime": 73584009000
  },
  {
    "commentId": 153627,
    "codingamerId": 5569265,
    "commentableId": 30825495,
    "responseCount": 0,
    "upVotes": 0,
    "downVotes": 0,
    "votableId": 31229745,
    "userVoteValue": 0,
    "nickname": "Braxis27",
    "content": "✅ Approved the contribution.\nComment: Fun puzzle",
    "codingamerHandle": "435ae1a690c0c42fba18c94364bcb5095629655",
    "avatar": 112962981037815,
    "elapsedTime": 73606405000
  },
  {
    "commentId": 153624,
    "codingamerId": 4698040,
    "commentableId": 30825495,
    "responseCount": 0,
    "upVotes": 0,
    "downVotes": 0,
    "votableId": 31228861,
    "userVoteValue": 0,
    "nickname": "[CG]Onora",
    "content": "✅ Approved the contribution.\nComment: Nice work ! Need some reflexion but easilly doable in 5min",
    "codingamerHandle": "6b2a726e9a6eb6da1d1d5ae64b7f7f2d0408964",
    "avatar": 137624449716376,
    "elapsedTime": 73610619000
  },
  {
    "commentId": 153571,
    "codingamerId": 5569265,
    "commentableId": 30825495,
    "responseCount": 0,
    "upVotes": 0,
    "downVotes": 1,
    "votableId": 31223332,
    "userVoteValue": 0,
    "nickname": "Braxis27",
    "content": "This is a really good idea for a puzzle",
    "codingamerHandle": "435ae1a690c0c42fba18c94364bcb5095629655",
    "avatar": 112962981037815,
    "elapsedTime": 73649657000
  },
  {
    "commentId": 153344,
    "codingamerId": 5670129,
    "commentableId": 30825495,
    "responseCount": 0,
    "upVotes": 0,
    "downVotes": 0,
    "votableId": 31213691,
    "userVoteValue": 0,
    "nickname": "niefba",
    "content": "✅ Approved the contribution.\nComment: Nice job!",
    "codingamerHandle": "9b2bde7f248e7d70602ad00cd756947f9210765",
    "avatar": 110388343255496,
    "elapsedTime": 73714535000
  },
  {
    "commentId": 153016,
    "codingamerId": 5670129,
    "commentableId": 30825495,
    "responseCount": 1,
    "upVotes": 0,
    "downVotes": 0,
    "votableId": 31202844,
    "userVoteValue": 0,
    "nickname": "niefba",
    "content": "Hello,\nIt seems to me that to calculate speed, you have to use the perimeter and not the diameter of the wheel. The test results and the proposed solution are therefore missing a pi factor.\n\nYou could also supply the wheel perimeter instead of the diameter.\n\nBest regards.",
    "codingamerHandle": "9b2bde7f248e7d70602ad00cd756947f9210765",
    "avatar": 110388343255496,
    "elapsedTime": 73797099000
  },
  {
    "commentId": 147109,
    "codingamerId": 2874091,
    "commentableId": 30825495,
    "responseCount": 0,
    "upVotes": 1,
    "downVotes": 0,
    "votableId": 30972071,
    "userVoteValue": 0,
    "nickname": "5DN1L",
    "content": "Goal section\n* Please fix the following words:\n   • emit => emits\n   • turn => turned\n   • the current => The current\n   • keep => keeps\n   • sec => seconds\n\n* Suggest to change \"round 1digit\" to \"rounded to 1 decimal place\".\n\nInput section\n* Please format \"N\" in Line 3 as a [[variable]].\n\n* Please change \"separated [[t]]\" to \"[[t]] separated\".\n\nOutput section\n* Please change \"sec\" to \"seconds\".\n\n* Suggest to change \"round 1digit\" to \"rounded to 1 decimal place\".\n\nThanks.",
    "codingamerHandle": "bbb8f47ea4601179303c20acdbf5fb6c1904782",
    "onlineSince": 1770727666105,
    "avatar": 134264063920528,
    "elapsedTime": 75611336000
  },
  {
    "commentId": 153343,
    "codingamerId": 5296961,
    "commentableId": 30825495,
    "responseCount": 0,
    "upVotes": 1,
    "downVotes": 0,
    "parentCommentId": 153016,
    "votableId": 31213148,
    "userVoteValue": 0,
    "nickname": "bzhen",
    "content": "You are completely right,\nI changed the parameter 'Diameter' description for 'Perimeter'.",
    "codingamerHandle": "a9ec9d9fbe80a0a0c47c878fe0c72da01696925",
    "avatar": 135981644890389,
    "elapsedTime": 73717404000
  },
  {
    "commentId": 153874,
    "codingamerId": 5296961,
    "commentableId": 30825495,
    "responseCount": 0,
    "upVotes": 1,
    "downVotes": 0,
    "parentCommentId": 153671,
    "votableId": 31236186,
    "userVoteValue": 0,
    "nickname": "bzhen",
    "content": "You are right, there was an error in the solution,\nIt should be buffer[-1]-buffer[0]. There is no reason of ignoring first value.\nI corrected the solution and expected value for each tests.",
    "codingamerHandle": "a9ec9d9fbe80a0a0c47c878fe0c72da01696925",
    "avatar": 135981644890389,
    "elapsedTime": 73544654000
  },
  {
    "commentId": 218417,
    "codingamerId": 5296961,
    "commentableId": 30825495,
    "responseCount": 0,
    "upVotes": 0,
    "downVotes": 1,
    "parentCommentId": 218285,
    "votableId": 33898526,
    "userVoteValue": 0,
    "nickname": "bzhen",
    "content": "The latest test case is arguable. If there is only 1tic, the distance is 0 < D< 2*P.\nin this case,  max speed= 2*P[m]*3.6/5 = 0.95 km/h.\n\nOfc there is not exactly 5seconds between last and first tic due to the sensor principle, but the statement indicate that only tics that occur during the last 5secondes are keep in the buffer.",
    "codingamerHandle": "a9ec9d9fbe80a0a0c47c878fe0c72da01696925",
    "avatar": 135981644890389,
    "elapsedTime": 53298455000
  },
  {
    "commentId": 218418,
    "codingamerId": 3893564,
    "commentableId": 30825495,
    "responseCount": 0,
    "upVotes": 1,
    "downVotes": 0,
    "parentCommentId": 218285,
    "votableId": 33898571,
    "userVoteValue": 0,
    "nickname": "Andriamanitra",
    "content": "But the statement does not say \"calculate the average speed between first and last tic\", it says \"Calculate the average speed of bicycle in km/h for the last 5 seconds\" which is simply not the case. It needs to be fixed.",
    "codingamerHandle": "8931375f2caabaa3c46fc9401a856edf4653983",
    "avatar": 46641547586781,
    "elapsedTime": 53298102000
  },
  {
    "commentId": 288178,
    "codingamerId": 4851925,
    "commentableId": 30825495,
    "responseCount": 0,
    "upVotes": 0,
    "downVotes": 0,
    "parentCommentId": 218285,
    "votableId": 35474786,
    "userVoteValue": 0,
    "nickname": "Nik0Lo",
    "content": "I agree 100%. The statement needs to be worded a bit better.",
    "codingamerHandle": "277f18b0e35732026ad6d570da7764975291584",
    "avatar": 82773946914933,
    "elapsedTime": 39964642000
  }
]