[
  {
    "commentId": 47485,
    "codingamerId": 878974,
    "commentableId": 2975551,
    "responseCount": 0,
    "upVotes": 0,
    "downVotes": 0,
    "votableId": 18921821,
    "userVoteValue": 0,
    "nickname": "nicola",
    "content": "I added the [[permutations]] and [[lists]] tags.",
    "codingamerHandle": "21bf42f790de293c3aef398f18cd2627479878",
    "onlineSince": 1770701591260,
    "avatar": 26090852120005,
    "elapsedTime": 146887992000
  },
  {
    "commentId": 3265,
    "codingamerId": 552776,
    "commentableId": 2975551,
    "responseCount": 0,
    "upVotes": 1,
    "downVotes": 0,
    "votableId": 3051135,
    "userVoteValue": 0,
    "nickname": "player_one",
    "content": "I've solved it, and voted to accept. A bit on the easy side, but reasonable. Thanks for the submission.",
    "codingamerHandle": "fefb3b0a360d9451bde5553900470e2d677255",
    "avatar": 52487021619351,
    "elapsedTime": 302359941000
  },
  {
    "commentId": 3252,
    "codingamerId": 552776,
    "commentableId": 2975551,
    "responseCount": 1,
    "upVotes": 1,
    "downVotes": 0,
    "votableId": 3047903,
    "userVoteValue": 0,
    "nickname": "player_one",
    "content": "I have changed the example from 3 to 5 since the 3 sequence doesn't illustrate the nature of the permutation very well. It simply looks like the numbers are rolling to the right:\n\n1,2,3   3,1,2   2,3,1   1,2,3",
    "codingamerHandle": "fefb3b0a360d9451bde5553900470e2d677255",
    "avatar": 52487021619351,
    "elapsedTime": 302398604000
  },
  {
    "commentId": 3222,
    "codingamerId": 155929,
    "commentableId": 2975551,
    "responseCount": 4,
    "upVotes": 0,
    "downVotes": 0,
    "votableId": 3041035,
    "userVoteValue": 0,
    "nickname": "[CG]jupoulton",
    "content": "as follow\"S\"",
    "codingamerHandle": "d39436e9a23b5060ed3efaf1c24b4ba8929551",
    "avatar": 9399538004630,
    "elapsedTime": 302489106000
  },
  {
    "commentId": 3217,
    "codingamerId": 154906,
    "commentableId": 2975551,
    "responseCount": 2,
    "upVotes": 1,
    "downVotes": 0,
    "votableId": 3039636,
    "userVoteValue": 0,
    "nickname": "JBM",
    "content": "Cool problem. I like it.\n\nThe statement is mostly good to go as is. The following could be improved at will:\n\n* emphasize the fact \"Nth line = initial sequence\" more than \"can go through permutations and stay the same\".  Right now, first sentence of second paragraph looks like a definition, but it's sufficient to make 4 a Queneau number, which turns out not to be the case following the last paragraph.\n\n* \"separeted\". Try \"as a comma-separated sequence\"",
    "codingamerHandle": "0d71f9df5da706f9f77c07c34d12480e609451",
    "elapsedTime": 302501441000
  },
  {
    "commentId": 3218,
    "codingamerId": 199979,
    "commentableId": 2975551,
    "responseCount": 0,
    "upVotes": 0,
    "downVotes": 0,
    "parentCommentId": 3217,
    "votableId": 3039644,
    "userVoteValue": 0,
    "nickname": "VonRickroll",
    "content": "Thanks for your advice.\n\nWhat about \"The Nth line is always the same as the initial sequence, or else the number is not a Queneau Number.\", isn't this sentence enough to emphasize ?\n\nUpdated the statement with \"as a comma-separated sequence\"",
    "codingamerHandle": "1f902a3213291dfd0de802207d362bdf979991",
    "avatar": 4699081038708,
    "elapsedTime": 302501307000
  },
  {
    "commentId": 3223,
    "codingamerId": 199979,
    "commentableId": 2975551,
    "responseCount": 0,
    "upVotes": 2,
    "downVotes": 0,
    "parentCommentId": 3222,
    "votableId": 3041041,
    "userVoteValue": 0,
    "nickname": "VonRickroll",
    "content": "I sit literally one metre across from you.",
    "codingamerHandle": "1f902a3213291dfd0de802207d362bdf979991",
    "avatar": 4699081038708,
    "elapsedTime": 302489055000
  },
  {
    "commentId": 3253,
    "codingamerId": 199979,
    "commentableId": 2975551,
    "responseCount": 0,
    "upVotes": 0,
    "downVotes": 0,
    "parentCommentId": 3252,
    "votableId": 3047907,
    "userVoteValue": 0,
    "nickname": "VonRickroll",
    "content": "Great! Thanks a lot!",
    "codingamerHandle": "1f902a3213291dfd0de802207d362bdf979991",
    "avatar": 4699081038708,
    "elapsedTime": 302398574000
  },
  {
    "commentId": 3225,
    "codingamerId": 155929,
    "commentableId": 2975551,
    "responseCount": 0,
    "upVotes": 0,
    "downVotes": 0,
    "parentCommentId": 3222,
    "votableId": 3041167,
    "userVoteValue": 0,
    "nickname": "[CG]jupoulton",
    "content": "metre :p",
    "codingamerHandle": "d39436e9a23b5060ed3efaf1c24b4ba8929551",
    "avatar": 9399538004630,
    "elapsedTime": 302487796000
  },
  {
    "commentId": 3226,
    "codingamerId": 199979,
    "commentableId": 2975551,
    "responseCount": 0,
    "upVotes": 0,
    "downVotes": 1,
    "parentCommentId": 3222,
    "votableId": 3041173,
    "userVoteValue": 0,
    "nickname": "VonRickroll",
    "content": "I don't know what you're talking about. Mate.",
    "codingamerHandle": "1f902a3213291dfd0de802207d362bdf979991",
    "avatar": 4699081038708,
    "elapsedTime": 302487747000
  },
  {
    "commentId": 3227,
    "codingamerId": 155929,
    "commentableId": 2975551,
    "responseCount": 0,
    "upVotes": 0,
    "downVotes": 0,
    "parentCommentId": 3222,
    "votableId": 3041349,
    "userVoteValue": 0,
    "nickname": "[CG]jupoulton",
    "content": "Cheater",
    "codingamerHandle": "d39436e9a23b5060ed3efaf1c24b4ba8929551",
    "avatar": 9399538004630,
    "elapsedTime": 302486212000
  },
  {
    "commentId": 3219,
    "codingamerId": 154906,
    "commentableId": 2975551,
    "responseCount": 0,
    "upVotes": 1,
    "downVotes": 0,
    "parentCommentId": 3217,
    "votableId": 3040504,
    "userVoteValue": 0,
    "nickname": "JBM",
    "content": "That fragment you quote is the right part. The problem is it's the last part of the statement, despite being crucial information that invalidates the first definition.\n\nFixing the first sentence so that it actually excludes non-Q numbers would be enough. For example, change \"stay the same\" to \"come back to [1..N] in exactly N iterations\"",
    "codingamerHandle": "0d71f9df5da706f9f77c07c34d12480e609451",
    "elapsedTime": 302493416000
  }
]