{
  "id": 7001,
  "activeVersion": 15,
  "score": 2,
  "votableId": 19007300,
  "codingamerId": 1567943,
  "views": 405,
  "commentableId": 18908561,
  "title": "Difference of Squares",
  "status": "ACCEPTED",
  "type": "CLASHOFCODE",
  "nickname": "LazyMammal",
  "publicHandle": "7001fa1becaece3de7ec0846cef2af2d1dbf",
  "codingamerHandle": "f0bc8a5294a05437ffe941f4217dc12d3497651",
  "lastVersion": {
    "version": 15,
    "autocloseTime": 1626979587670,
    "data": {
      "title": "Difference of Squares",
      "topics": [],
      "fastest": true,
      "reverse": false,
      "shortest": true,
      "solution": "#include <iostream>\n\nusing namespace std;\n\nint main()\n{\n    int N;\n    cin >> N;\n    cin.ignore();\n\n    for (int d = 0; d <= 2; d++)\n        for (int B = 0; B <= 50000000; B++)\n        {\n            int A = B + d;\n            if (A * A - B * B == N * N)\n            {\n                cout << A << \" \" << B << endl;\n                return 0;\n            }\n        }\n}",
      "statement": "Given [[N]], find a solution [[A]], [[B]] to the equation: {{[[N]]^2 = [[A]]^2 - [[B]]^2}}\n\nIf multiple solutions are possible choose the one with smallest difference:  {{d = [[A]] - [[B]]}}\n\nIt may also be helpful to consider the above difference when solving this clash...",
      "testCases": [
        {
          "title": "Three",
          "isTest": true,
          "testIn": "3",
          "testOut": "5 4",
          "isValidator": false,
          "needValidation": true
        },
        {
          "title": "Five",
          "isTest": false,
          "testIn": "5",
          "testOut": "13 12",
          "isValidator": true,
          "needValidation": true
        },
        {
          "title": "Four",
          "isTest": true,
          "testIn": "4",
          "testOut": "5 3",
          "isValidator": false,
          "needValidation": true
        },
        {
          "title": "Six",
          "isTest": false,
          "testIn": "6",
          "testOut": "10 8",
          "isValidator": true,
          "needValidation": true
        },
        {
          "title": "Zero",
          "isTest": true,
          "testIn": "0",
          "testOut": "0 0",
          "isValidator": false,
          "needValidation": true
        },
        {
          "title": "Zero",
          "isTest": false,
          "testIn": "0",
          "testOut": "0 0",
          "isValidator": true,
          "needValidation": true
        },
        {
          "title": "One",
          "isTest": true,
          "testIn": "1",
          "testOut": "1 0",
          "isValidator": false,
          "needValidation": true
        },
        {
          "title": "Two",
          "isTest": false,
          "testIn": "2",
          "testOut": "2 0",
          "isValidator": true,
          "needValidation": true
        },
        {
          "title": "Test 15",
          "isTest": true,
          "testIn": "15",
          "testOut": "113 112",
          "isValidator": false,
          "needValidation": true
        },
        {
          "title": "Validator 21",
          "isTest": false,
          "testIn": "21",
          "testOut": "221 220",
          "isValidator": true,
          "needValidation": true
        },
        {
          "title": "Test 28",
          "isTest": true,
          "testIn": "28",
          "testOut": "197 195",
          "isValidator": false,
          "needValidation": true
        },
        {
          "title": "Validator 32",
          "isTest": false,
          "testIn": "32",
          "testOut": "257 255",
          "isValidator": true,
          "needValidation": true
        },
        {
          "title": "Test 9999",
          "isTest": true,
          "testIn": "9999",
          "testOut": "49990001 49990000",
          "isValidator": false,
          "needValidation": true
        },
        {
          "title": "Validator 9997",
          "isTest": false,
          "testIn": "9997",
          "testOut": "49970005 49970004",
          "isValidator": true,
          "needValidation": true
        },
        {
          "title": "Test 10000",
          "isTest": true,
          "testIn": "10000",
          "testOut": "25000001 24999999",
          "isValidator": false,
          "needValidation": true
        },
        {
          "title": "Validator 9998",
          "isTest": false,
          "testIn": "9998",
          "testOut": "24990002 24990000",
          "isValidator": true,
          "needValidation": true
        }
      ],
      "constraints": "0 ≤ [[N]] ≤ 10000\n0 ≤ [[B]] ≤ [[A]]",
      "stubGenerator": "read N:int\nwrite 5 4",
      "inputDescription": "Integer [[N]] for the left side of the equation.",
      "solutionLanguage": "C++",
      "outputDescription": "Two space separated non-negative integers [[A]] and [[B]] for the right side of the equation."
    },
    "draft": false,
    "readyForModeration": true,
    "statementHTML": "<div class=\"statement-body\">\n<div class=\"statement-section statement-goal\">\n   <h2><span class=\"icon icon-goal\">&nbsp;</span><span>Goal </span></h2>\n   <span class=\"question-statement\">Given <var>N</var>, find a solution <var>A</var>, <var>B</var> to the equation: <const><var>N</var>^2 = <var>A</var>^2 - <var>B</var>^2</const><br><br>If multiple solutions are possible choose the one with smallest difference:  <const>d = <var>A</var> - <var>B</var></const><br><br>It may also be helpful to consider the above difference when solving this clash...</span>\n</div>\n<div class=\"statement-section statement-protocol\">\n   <div class=\"blk\">\n      <div class=\"title\">Input</div>\n      <div class=\"question-statement-input\">Integer <var>N</var> for the left side of the equation.</div>\n   </div>\n   <div class=\"blk\">\n      <div class=\"title\">Output</div>\n      <div class=\"question-statement-output\">Two space separated non-negative integers <var>A</var> and <var>B</var> for the right side of the equation.</div>\n   </div>\n   <div class=\"blk\">\n      <div class=\"title\">Constraints</div>\n      <div class=\"question-statement-constraints\">0 &le; <var>N</var> &le; 10000<br>0 &le; <var>B</var> &le; <var>A</var></div>\n   </div>\n   <div class=\"blk\">\n      <div class=\"title\">Example</div>\n      <div class=\"statement-inout\">\n         <div class=\"statement-inout-in\">\n            <div class=\"title\">Input</div>\n            <pre class=\"question-statement-example-in\">3</pre>\n         </div>\n         <div class=\"statement-inout-out\">\n            <div class=\"title\">Output</div>\n            <pre class=\"question-statement-example-out\">5 4</pre>\n         </div>\n      </div>\n   </div>\n</div>"
  },
  "validatedFor": 146105285872,
  "avatar": 54419089430083,
  "commentCount": 39,
  "upVotes": 7,
  "downVotes": 5,
  "validateAction": {
    "actionId": 572026,
    "progress": 1,
    "alreadyDone": false
  },
  "denyAction": {
    "actionId": 572304,
    "progress": 0.3333333333333333,
    "alreadyDone": false
  },
  "statusHistory": [
    {
      "status": "ACCEPTED",
      "date": 1624625147992,
      "data": {
        "author": "ACTION"
      }
    }
  ],
  "editable": true,
  "draft": false,
  "readyForModeration": true
}